coordinate_descent_attention/__init__.py
coordinate_descent_attention/autoregressive_wrapper.py
coordinate_descent_attention/coordinate_descent_attention.py
coordinate_descent_attention-0.0.11.dist-info/LICENSE
coordinate_descent_attention-0.0.11.dist-info/METADATA
coordinate_descent_attention-0.0.11.dist-info/WHEEL
coordinate_descent_attention-0.0.11.dist-info/top_level.txt
coordinate_descent_attention-0.0.11.dist-info/RECORD
