Metadata-Version: 2.1
Name: coordinate-descent-attention
Version: 0.0.11
Summary: Coordinate Descent Attention - Pytorch
Home-page: https://github.com/lucidrains/coodinate-descent-attention
Author: Phil Wang
Author-email: lucidrains@gmail.com
License: MIT
Keywords: artificial intelligence,deep learning,attention mechanism
Classifier: Development Status :: 4 - Beta
Classifier: Intended Audience :: Developers
Classifier: Topic :: Scientific/Engineering :: Artificial Intelligence
Classifier: License :: OSI Approved :: MIT License
Classifier: Programming Language :: Python :: 3.6
License-File: LICENSE
Requires-Dist: einops (>=0.6.1)
Requires-Dist: torch (>=1.6)
Requires-Dist: colt5-attention (>=0.9.0)
